<?xml version="1.0" encoding="UTF-8"?>
<site generator-info-name="WebGrab+Plus/w MDB &amp; REX Postprocess -- version 1.1.1/35 -- Jan van Straaten" site="skynet.lt">
  <channels>
    <channel update="i" site="skynet.lt" site_id="1" xmltv_id="LRT">LRT</channel>
    <channel update="i" site="skynet.lt" site_id="2" xmltv_id="LRT Kultūra">LRT Kultūra</channel>
    <channel update="i" site="skynet.lt" site_id="3" xmltv_id="TV3">TV3</channel>
    <channel update="i" site="skynet.lt" site_id="4" xmltv_id="LNK">LNK</channel>
    <channel update="i" site="skynet.lt" site_id="5" xmltv_id="BTV">BTV</channel>
    <channel update="i" site="skynet.lt" site_id="6" xmltv_id="TV1">TV1</channel>
    <channel update="i" site="skynet.lt" site_id="7" xmltv_id="TV 6">TV 6</channel>
    <channel update="i" site="skynet.lt" site_id="8" xmltv_id="Lryto TV">Lryto TV</channel>
    <channel update="i" site="skynet.lt" site_id="9" xmltv_id="S plius">S plius</channel>
    <channel update="i" site="skynet.lt" site_id="11" xmltv_id="Euronews">Euronews</channel>
    <channel update="i" site="skynet.lt" site_id="12" xmltv_id="CNN">CNN</channel>
    <channel update="i" site="skynet.lt" site_id="13" xmltv_id="BBC World">BBC World</channel>
    <channel update="i" site="skynet.lt" site_id="14" xmltv_id="DW">DW</channel>
    <channel update="i" site="skynet.lt" site_id="15" xmltv_id="Bloomberg">Bloomberg</channel>
    <channel update="i" site="skynet.lt" site_id="17" xmltv_id="PBK">PBK</channel>
    <channel update="i" site="skynet.lt" site_id="18" xmltv_id="TVCI">TVCI</channel>
    <channel update="i" site="skynet.lt" site_id="19" xmltv_id="RenTV">RenTV</channel>
    <channel update="i" site="skynet.lt" site_id="21" xmltv_id="TDK">TDK</channel>
    <channel update="i" site="skynet.lt" site_id="22" xmltv_id="RBK">RBK</channel>
    <channel update="i" site="skynet.lt" site_id="23" xmltv_id="CN">CN</channel>
    <channel update="i" site="skynet.lt" site_id="24" xmltv_id="MTV">MTV</channel>
    <channel update="i" site="skynet.lt" site_id="25" xmltv_id="Žvaigždė">Žvaigždė</channel>
    <channel update="i" site="skynet.lt" site_id="26" xmltv_id="MCM TOP">MCM TOP</channel>
    <channel update="i" site="skynet.lt" site_id="27" xmltv_id="Fox Life">Fox Life</channel>
    <channel update="i" site="skynet.lt" site_id="28" xmltv_id="MEZZO">MEZZO</channel>
    <channel update="i" site="skynet.lt" site_id="29" xmltv_id="Discovery">Discovery</channel>
    <channel update="i" site="skynet.lt" site_id="30" xmltv_id="Animal">Animal</channel>
    <channel update="i" site="skynet.lt" site_id="33" xmltv_id="TV Pol">TV Pol</channel>
    <channel update="i" site="skynet.lt" site_id="34" xmltv_id="Fashion">Fashion</channel>
    <channel update="i" site="skynet.lt" site_id="35" xmltv_id="Penki TV">Penki TV</channel>
    <channel update="i" site="skynet.lt" site_id="36" xmltv_id="Travel">Travel</channel>
    <channel update="i" site="skynet.lt" site_id="37" xmltv_id="SAT 1">SAT 1</channel>
    <channel update="i" site="skynet.lt" site_id="38" xmltv_id="France 24">France 24</channel>
    <channel update="i" site="skynet.lt" site_id="39" xmltv_id="Eurosport">Eurosport</channel>
    <channel update="i" site="skynet.lt" site_id="40" xmltv_id="Balticum TV">Balticum TV</channel>
    <channel update="i" site="skynet.lt" site_id="41" xmltv_id="ESP 2">ESP 2</channel>
    <channel update="i" site="skynet.lt" site_id="44" xmltv_id="Rai Uno">Rai Uno</channel>
    <channel update="i" site="skynet.lt" site_id="47" xmltv_id="Naše kino">Naše kino</channel>
    <channel update="i" site="skynet.lt" site_id="58" xmltv_id="Info TV">Info TV</channel>
    <channel update="i" site="skynet.lt" site_id="59" xmltv_id="Liuks!">Liuks!</channel>
    <channel update="i" site="skynet.lt" site_id="60" xmltv_id="RTVi">RTVi</channel>
    <channel update="i" site="skynet.lt" site_id="61" xmltv_id="Oxota">Oxota</channel>
    <channel update="i" site="skynet.lt" site_id="62" xmltv_id="Auto Plius">Auto Plius</channel>
    <channel update="i" site="skynet.lt" site_id="63" xmltv_id="Interesnoje TV">Interesnoje TV</channel>
    <channel update="i" site="skynet.lt" site_id="64" xmltv_id="Star!">Star!</channel>
    <channel update="i" site="skynet.lt" site_id="70" xmltv_id="National Geographic">National Geographic</channel>
    <channel update="i" site="skynet.lt" site_id="71" xmltv_id="Balticum Auksinis">Balticum Auksinis</channel>
    <channel update="i" site="skynet.lt" site_id="72" xmltv_id="Sky News">Sky News</channel>
    <channel update="i" site="skynet.lt" site_id="73" xmltv_id="Russia Today">Russia Today</channel>
    <channel update="i" site="skynet.lt" site_id="75" xmltv_id="Nat Geo Wild">Nat Geo Wild</channel>
    <channel update="i" site="skynet.lt" site_id="76" xmltv_id="Syfy Universal">Syfy Universal</channel>
    <channel update="i" site="skynet.lt" site_id="77" xmltv_id="Universal">Universal</channel>
    <channel update="i" site="skynet.lt" site_id="78" xmltv_id="Duck TV">Duck TV</channel>
    <channel update="i" site="skynet.lt" site_id="79" xmltv_id="Boomerang">Boomerang</channel>
    <channel update="i" site="skynet.lt" site_id="81" xmltv_id="Da Vinci">Da Vinci</channel>
    <channel update="i" site="skynet.lt" site_id="82" xmltv_id="Discovery Science">Discovery Science</channel>
    <channel update="i" site="skynet.lt" site_id="83" xmltv_id="Discovery World">Discovery World</channel>
    <channel update="i" site="skynet.lt" site_id="84" xmltv_id="TLC">TLC</channel>
    <channel update="i" site="skynet.lt" site_id="85" xmltv_id="JimJam">JimJam</channel>
    <channel update="i" site="skynet.lt" site_id="86" xmltv_id="Extreme Sports">Extreme Sports</channel>
    <channel update="i" site="skynet.lt" site_id="87" xmltv_id="Zone Reality">Zone Reality</channel>
    <channel update="i" site="skynet.lt" site_id="88" xmltv_id="Zone Romantica">Zone Romantica</channel>
    <channel update="i" site="skynet.lt" site_id="89" xmltv_id="Pro 7">Pro 7</channel>
    <channel update="i" site="skynet.lt" site_id="92" xmltv_id="History HD">History HD</channel>
    <channel update="i" site="skynet.lt" site_id="93" xmltv_id="VH1">VH1</channel>
    <channel update="i" site="skynet.lt" site_id="94" xmltv_id="MTV Music 24">MTV Music 24</channel>
    <channel update="i" site="skynet.lt" site_id="95" xmltv_id="Duck TV HD">Duck TV HD</channel>
    <channel update="i" site="skynet.lt" site_id="99" xmltv_id="Diva Universal">Diva Universal</channel>
    <channel update="i" site="skynet.lt" site_id="101" xmltv_id="History">History</channel>
    <channel update="i" site="skynet.lt" site_id="102" xmltv_id="I-Concerts HD">I-Concerts HD</channel>
    <channel update="i" site="skynet.lt" site_id="103" xmltv_id="Fox Crime">Fox Crime</channel>
    <channel update="i" site="skynet.lt" site_id="104" xmltv_id="Silver Baltic">Silver Baltic</channel>
    <channel update="i" site="skynet.lt" site_id="105" xmltv_id="Showtime">Showtime</channel>
    <channel update="i" site="skynet.lt" site_id="106" xmltv_id="Invest Discovery">Invest Discovery</channel>
    <channel update="i" site="skynet.lt" site_id="107" xmltv_id="Discovery HD">Discovery HD</channel>
    <channel update="i" site="skynet.lt" site_id="115" xmltv_id="RuMusic">RuMusic</channel>
    <channel update="i" site="skynet.lt" site_id="116" xmltv_id="A-ONE">A-ONE</channel>
    <channel update="i" site="skynet.lt" site_id="117" xmltv_id="NTV Mir">NTV Mir</channel>
    <channel update="i" site="skynet.lt" site_id="118" xmltv_id="Belarus TV">Belarus TV</channel>
    <channel update="i" site="skynet.lt" site_id="119" xmltv_id="Kobra TV HD">Kobra TV HD</channel>
    <channel update="i" site="skynet.lt" site_id="120" xmltv_id="RTR-Planeta">RTR-Planeta</channel>
    <channel update="i" site="skynet.lt" site_id="135" xmltv_id="TV 8">TV 8</channel>
    <channel update="i" site="skynet.lt" site_id="254" xmltv_id="Viasat Sport Baltic">Viasat Sport Baltic</channel>
    <channel update="i" site="skynet.lt" site_id="256" xmltv_id="Premier League HD">Premier League HD</channel>
    <channel update="i" site="skynet.lt" site_id="257" xmltv_id="Viasat Golf">Viasat Golf</channel>
    <channel update="i" site="skynet.lt" site_id="265" xmltv_id="SET">SET</channel>
    <channel update="i" site="skynet.lt" site_id="266" xmltv_id="Lolo TV">Lolo TV</channel>
    <channel update="i" site="skynet.lt" site_id="267" xmltv_id="TV1000">TV1000</channel>
    <channel update="i" site="skynet.lt" site_id="268" xmltv_id="TV1000 RusskojeKino">TV1000 RusskojeKino</channel>
    <channel update="i" site="skynet.lt" site_id="269" xmltv_id="TV1000 Action">TV1000 Action</channel>
    <channel update="i" site="skynet.lt" site_id="270" xmltv_id="TV1000 Premium">TV1000 Premium</channel>
    <channel update="i" site="skynet.lt" site_id="271" xmltv_id="Viasat Motor">Viasat Motor</channel>
  </channels>
</site>