<?xml version="1.0" encoding="UTF-8"?>
<site generator-info-name="WebGrab+Plus/w MDB &amp; REX Postprocess -- version V4.2.3.6 -- Jan van Straaten" site="tvpink.si">
  <channels>
    <channel update="i" site="tvpink.si" site_id="Film" xmltv_id="Pink Film">Pink Film</channel>
    <channel update="i" site="tvpink.si" site_id="Extra" xmltv_id="Pink Extra">Pink Extra</channel>
    <channel update="i" site="tvpink.si" site_id="Plus" xmltv_id="Pink Plus">Pink Plus</channel>
    <channel update="i" site="tvpink.si" site_id="Folk" xmltv_id="Pink Folk">Pink Folk</channel>
    <channel update="i" site="tvpink.si" site_id="Folk 2" xmltv_id="Pink Folk 2">Pink Folk 2</channel>
    <channel update="i" site="tvpink.si" site_id="World" xmltv_id="Pink World">Pink World</channel>
    <channel update="i" site="tvpink.si" site_id="Music" xmltv_id="Pink Music">Pink Music</channel>
    <channel update="i" site="tvpink.si" site_id="Music_2" xmltv_id="Pink Music 2">Pink Music 2</channel>
    <channel update="i" site="tvpink.si" site_id="Kids" xmltv_id="Pink Kids">Pink Kids</channel>
    <channel update="i" site="tvpink.si" site_id="Zabava" xmltv_id="Pink Zabava">Pink Zabava</channel>
    <channel update="i" site="tvpink.si" site_id="Reality" xmltv_id="Pink Reality">Pink Reality</channel>
    <channel update="i" site="tvpink.si" site_id="Serije" xmltv_id="Pink Serije">Pink Serije</channel>
    <channel update="i" site="tvpink.si" site_id="Fashion" xmltv_id="Pink Fashion">Pink Fashion</channel>
    <channel update="i" site="tvpink.si" site_id="Show" xmltv_id="Pink Show">Pink Show</channel>
    <channel update="i" site="tvpink.si" site_id="Hits_1" xmltv_id="Pink Hits 1">Pink Hits 1</channel>
    <channel update="i" site="tvpink.si" site_id="Hits_2" xmltv_id="Pink Hits 2">Pink Hits 2</channel>
    <channel update="i" site="tvpink.si" site_id="Roll" xmltv_id="Pink'n'Roll">Pink'n'Roll</channel>
    <channel update="i" site="tvpink.si" site_id="Koncert" xmltv_id="Pink Koncert">Pink Koncert</channel>
    <channel update="i" site="tvpink.si" site_id="Bravo" xmltv_id="Bravo Music">Bravo Music</channel>
    <channel update="i" site="tvpink.si" site_id="Pink_SI" xmltv_id="Pink Si">Pink Si</channel>
  </channels>
</site>